{
  "success": true,
  "data": {
    "id": "FOL-1001",
    "groupId": "GRP-260527-01",
    "companyId": "COMP-1001",
    "ownerName": "Samsung Tech Conference 2026",
    "status": "open",
    "balance": {
      "amount": 867,
      "currency": "USD"
    },
    "charges": [
      {
        "id": "FOL-1001-CHG-1",
        "type": "room",
        "desc": "OT 1401 room charge",
        "reservationId": "RSV-GRP-260527-01-1401",
        "roomId": "OT-1401",
        "amount": {
          "amount": 255,
          "currency": "USD"
        }
      },
      {
        "id": "FOL-1001-CHG-2",
        "type": "room",
        "desc": "FT 0801 room charge",
        "reservationId": "RSV-GRP-260527-01-0801",
        "roomId": "FT-0801",
        "amount": {
          "amount": 255,
          "currency": "USD"
        }
      },
      {
        "id": "FOL-1001-CHG-3",
        "type": "fnb",
        "desc": "Breakfast coupon",
        "groupId": "GRP-260527-01",
        "amount": {
          "amount": 357,
          "currency": "USD"
        }
      }
    ],
    "payments": [],
    "folioId": "FOL-1001",
    "folioType": "group",
    "guestName": "Samsung Tech Conference 2026",
    "roomNo": "Group",
    "roomIds": [
      "OT-1401",
      "FT-0801",
      "FT-0802",
      "FT-0803"
    ],
    "reservationIds": [
      "RSV-GRP-260527-01-1401",
      "RSV-GRP-260527-01-0801",
      "RSV-GRP-260527-01-0802",
      "RSV-GRP-260527-01-0803"
    ],
    "guestIds": [
      "G-1013",
      "G-1014",
      "G-260527010802",
      "G-260527010803"
    ],
    "issuedAt": "2026-06-09T09:30:00+09:00"
  },
  "meta": {
    "requestId": "REQ-FOLIO-FOL-1001",
    "tenantId": "TENANT-GRAND-SAIGON",
    "apiVersion": "v8",
    "generatedAt": "2026-06-09T09:00:00+09:00",
    "timezone": "Asia/Seoul",
    "currency": "USD"
  }
}
