{
  "success": true,
  "data": {
    "items": [
      {
        "id": "G-1001",
        "name": "Tran Linh",
        "nationality": "Vietnam",
        "tier": "Diamond",
        "visits": 24,
        "phone": "+84 91 888 9999",
        "email": "tran.linh@example.com",
        "status": "active",
        "document": { "type": "passport", "maskedNumber": "P****204", "status": "verified" },
        "specialNotes": "Prefers high floor, sparkling water, and late checkout.",
        "lastStayDate": "2026-06-02",
        "totalSpend": { "amount": 18900, "currency": "USD" },
        "tags": ["vip", "repeat"]
      },
      {
        "id": "G-1002",
        "name": "Al Rashid Omar",
        "nationality": "UAE",
        "tier": "Diamond",
        "visits": 18,
        "phone": "+971 50 123 4567",
        "email": "omar.rashid@example.com",
        "status": "active",
        "document": { "type": "passport", "maskedNumber": "P****811", "status": "verified" },
        "specialNotes": "Airport pickup and Arabic breakfast preference.",
        "lastStayDate": "2026-05-30",
        "totalSpend": { "amount": 22500, "currency": "USD" },
        "tags": ["vip", "airport-pickup"]
      },
      {
        "id": "G-1003",
        "name": "Garcia Miguel",
        "nationality": "Spain",
        "tier": "Diamond",
        "visits": 16,
        "phone": "+34 612 345 678",
        "email": "miguel.garcia@example.com",
        "status": "active",
        "document": { "type": "passport", "maskedNumber": "P****537", "status": "verified" },
        "specialNotes": "Golf package guest, prefers ocean view.",
        "lastStayDate": "2026-05-28",
        "totalSpend": { "amount": 14700, "currency": "USD" },
        "tags": ["golf", "vip"]
      },
      {
        "id": "G-1004",
        "name": "David Chen",
        "nationality": "Taiwan",
        "tier": "Platinum",
        "visits": 14,
        "phone": "+886 912 345 678",
        "email": "david.chen@example.com",
        "status": "active",
        "document": { "type": "passport", "maskedNumber": "P****332", "status": "verified" },
        "specialNotes": "Quiet room away from elevator.",
        "lastStayDate": "2026-05-26",
        "totalSpend": { "amount": 8400, "currency": "USD" },
        "tags": ["repeat"]
      },
      {
        "id": "G-1005",
        "name": "Tanaka Yuki",
        "nationality": "Japan",
        "tier": "Platinum",
        "visits": 11,
        "phone": "+81 80 1234 5678",
        "email": "yuki.tanaka@example.com",
        "status": "active",
        "document": { "type": "passport", "maskedNumber": "P****912", "status": "verified" },
        "specialNotes": "Prefers Japanese newspaper and green tea.",
        "lastStayDate": "2026-05-24",
        "totalSpend": { "amount": 7800, "currency": "USD" },
        "tags": ["repeat"]
      },
      {
        "id": "G-1006",
        "name": "Lee Hana",
        "nationality": "Korea",
        "tier": "Platinum",
        "visits": 9,
        "phone": "+82 10 1111 2222",
        "email": "hana.lee@example.com",
        "status": "active",
        "document": { "type": "id-card", "maskedNumber": "******-2******", "status": "verified" },
        "specialNotes": "Business traveler, early breakfast.",
        "lastStayDate": "2026-05-22",
        "totalSpend": { "amount": 5625, "currency": "USD" },
        "tags": ["business"]
      },
      {
        "id": "G-1007",
        "name": "Nguyen Michael",
        "nationality": "Vietnam",
        "tier": "Gold",
        "visits": 7,
        "phone": "+84 90 000 1001",
        "email": "michael.nguyen@example.com",
        "status": "active",
        "document": { "type": "passport", "maskedNumber": "P****789", "status": "verified" },
        "specialNotes": "Welcome amenity requested.",
        "lastStayDate": "2026-05-27",
        "totalSpend": { "amount": 4380, "currency": "USD" },
        "tags": ["repeat"]
      },
      {
        "id": "G-1008",
        "name": "Martinez Charles",
        "nationality": "USA",
        "tier": "Gold",
        "visits": 6,
        "phone": "+1 415 000 1004",
        "email": "charles.martinez@example.com",
        "status": "active",
        "document": { "type": "passport", "maskedNumber": "P****441", "status": "verified" },
        "specialNotes": "Prefers corner room.",
        "lastStayDate": "2026-05-25",
        "totalSpend": { "amount": 3640, "currency": "USD" },
        "tags": ["corporate"]
      },
      {
        "id": "G-1009",
        "name": "Park Soo Jin",
        "nationality": "Korea",
        "tier": "Gold",
        "visits": 5,
        "phone": "+82 10 5678 1234",
        "email": "soojin.park@example.com",
        "status": "active",
        "document": { "type": "id-card", "maskedNumber": "******-2******", "status": "verified" },
        "specialNotes": "Spa package buyer.",
        "lastStayDate": "2026-05-23",
        "totalSpend": { "amount": 2970, "currency": "USD" },
        "tags": ["spa"]
      },
      {
        "id": "G-1010",
        "name": "Wong Li",
        "nationality": "Hong Kong",
        "tier": "Gold",
        "visits": 8,
        "phone": "+852 9123 4567",
        "email": "li.wong@example.com",
        "status": "active",
        "document": { "type": "passport", "maskedNumber": "P****220", "status": "verified" },
        "specialNotes": "Mini-bar no alcohol.",
        "lastStayDate": "2026-05-21",
        "totalSpend": { "amount": 5720, "currency": "USD" },
        "tags": ["repeat"]
      },
      {
        "id": "G-1011",
        "name": "Kim Thi",
        "nationality": "Vietnam",
        "tier": "Standard",
        "visits": 2,
        "phone": "+84 90 000 1002",
        "email": "kim.thi@example.com",
        "status": "active",
        "document": { "type": "passport", "maskedNumber": "P****772", "status": "verified" },
        "specialNotes": "Late checkout preference.",
        "lastStayDate": "2026-05-20",
        "totalSpend": { "amount": 960, "currency": "USD" },
        "tags": ["repeat"]
      },
      {
        "id": "G-1012",
        "name": "Pham David",
        "nationality": "Vietnam",
        "tier": "Standard",
        "visits": 2,
        "phone": "+84 90 000 1003",
        "email": "david.pham@example.com",
        "status": "active",
        "document": { "type": "passport", "maskedNumber": "P****615", "status": "pending" },
        "specialNotes": "Document pending verification.",
        "lastStayDate": "2026-05-19",
        "totalSpend": { "amount": 720, "currency": "USD" },
        "tags": ["document-pending"]
      },
      {
        "id": "G-1013",
        "name": "Alexander Kim",
        "nationality": "Korea",
        "tier": "Standard",
        "visits": 3,
        "phone": "+82 10 9900 1401",
        "email": "alexander.kim@example.com",
        "status": "active",
        "document": { "type": "id-card", "maskedNumber": "******-*******", "status": "verified" },
        "specialNotes": "Nut allergy, hypoallergenic pillow.",
        "lastStayDate": "2026-05-18",
        "totalSpend": { "amount": 1280, "currency": "USD" },
        "tags": ["group-guest"]
      },
      {
        "id": "G-1014",
        "name": "Lee Hannah",
        "nationality": "Korea",
        "tier": "Standard",
        "visits": 3,
        "phone": "+82 10 9900 0801",
        "email": "hannah.lee@example.com",
        "status": "active",
        "document": { "type": "id-card", "maskedNumber": "******-*******", "status": "verified" },
        "specialNotes": "Late arrival after 21:00.",
        "lastStayDate": "2026-05-18",
        "totalSpend": { "amount": 1180, "currency": "USD" },
        "tags": ["group-guest"]
      },
      {
        "id": "G-1015",
        "name": "Mueller Klaus",
        "nationality": "Germany",
        "tier": "Standard",
        "visits": 2,
        "phone": "+49 170 123 4567",
        "email": "klaus.mueller@example.com",
        "status": "active",
        "document": { "type": "passport", "maskedNumber": "P****430", "status": "verified" },
        "specialNotes": "Prefers firm mattress.",
        "lastStayDate": "2026-05-16",
        "totalSpend": { "amount": 1560, "currency": "USD" },
        "tags": ["repeat"]
      },
      {
        "id": "G-1016",
        "name": "Sato Yuki",
        "nationality": "Japan",
        "tier": "Standard",
        "visits": 2,
        "phone": "+81 90 5555 6666",
        "email": "yuki.sato@example.com",
        "status": "active",
        "document": { "type": "passport", "maskedNumber": "P****119", "status": "verified" },
        "specialNotes": "Requests quiet room and green tea.",
        "lastStayDate": "2026-05-15",
        "totalSpend": { "amount": 1040, "currency": "USD" },
        "tags": ["repeat"]
      }
    ],
    "page": {
      "page": 1,
      "pageSize": 50,
      "total": 16,
      "totalPages": 1
    }
  },
  "meta": {
    "requestId": "REQ-GUESTS-LIST",
    "tenantId": "TENANT-GRAND-SAIGON",
    "apiVersion": "v8",
    "generatedAt": "2026-06-09T09:00:00+09:00",
    "timezone": "Asia/Seoul",
    "currency": "USD"
  }
}
