{
  "success": true,
  "data": {
    "items": [
      {
        "id": "standard",
        "name": "Standard",
        "label": {
          "ko": "일반",
          "en": "Standard"
        },
        "icon": "fa-user",
        "color": "#9CA3AF",
        "sortOrder": 10,
        "minSpend": 0,
        "minStays": 0,
        "benefits": {
          "roomDiscountPercent": 0,
          "earlyCheckIn": false,
          "lateCheckOut": false,
          "freeBreakfast": false,
          "roomUpgrade": "",
          "loungeAccess": false,
          "airportPickup": false,
          "welcomeAmenity": "",
          "pointEarnRate": "1x"
        }
      },
      {
        "id": "gold",
        "name": "Gold",
        "label": {
          "ko": "골드",
          "en": "Gold"
        },
        "icon": "fa-crown",
        "color": "#F59E0B",
        "sortOrder": 20,
        "minSpend": 2000,
        "minStays": 5,
        "benefits": {
          "roomDiscountPercent": 5,
          "earlyCheckIn": false,
          "lateCheckOut": true,
          "freeBreakfast": false,
          "roomUpgrade": "",
          "loungeAccess": false,
          "airportPickup": false,
          "welcomeAmenity": {
            "ko": "과일",
            "en": "Fruit"
          },
          "pointEarnRate": "1.5x"
        }
      },
      {
        "id": "platinum",
        "name": "Platinum",
        "label": {
          "ko": "플래티넘",
          "en": "Platinum"
        },
        "icon": "fa-star",
        "color": "#A78BFA",
        "sortOrder": 30,
        "minSpend": 5000,
        "minStays": 10,
        "benefits": {
          "roomDiscountPercent": 10,
          "earlyCheckIn": true,
          "lateCheckOut": true,
          "freeBreakfast": true,
          "roomUpgrade": {
            "ko": "가능 시",
            "en": "When available"
          },
          "loungeAccess": false,
          "airportPickup": false,
          "welcomeAmenity": {
            "ko": "과일+와인",
            "en": "Fruit + Wine"
          },
          "pointEarnRate": "2x"
        }
      },
      {
        "id": "diamond",
        "name": "Diamond",
        "label": {
          "ko": "다이아몬드",
          "en": "Diamond"
        },
        "icon": "fa-gem",
        "color": "#60A5FA",
        "sortOrder": 40,
        "minSpend": 10000,
        "minStays": 20,
        "benefits": {
          "roomDiscountPercent": 15,
          "earlyCheckIn": true,
          "lateCheckOut": true,
          "freeBreakfast": true,
          "roomUpgrade": {
            "ko": "우선",
            "en": "Priority"
          },
          "loungeAccess": true,
          "airportPickup": true,
          "welcomeAmenity": {
            "ko": "풀 패키지",
            "en": "Full Package"
          },
          "pointEarnRate": "3x"
        }
      }
    ],
    "page": {
      "page": 1,
      "pageSize": 50,
      "total": 4,
      "totalPages": 1
    }
  },
  "meta": {
    "requestId": "REQ-MEMBERSHIP-TIERS",
    "tenantId": "TENANT-GRAND-SAIGON",
    "apiVersion": "v8",
    "generatedAt": "2026-06-09T09:00:00+09:00",
    "timezone": "Asia/Seoul",
    "currency": "USD"
  }
}
