{
  "success": true,
  "data": {
    "items": [
      {
        "roomId": "OT-PH01",
        "roomNo": "PH01",
        "roomTypeId": "PTH",
        "date": "2026-06-09",
        "status": "in-house",
        "available": false,
        "rate": {
          "amount": 650,
          "currency": "USD"
        }
      },
      {
        "roomId": "OT-PH02",
        "roomNo": "PH02",
        "roomTypeId": "PTH",
        "date": "2026-06-09",
        "status": "in-house",
        "available": false,
        "rate": {
          "amount": 650,
          "currency": "USD"
        }
      },
      {
        "roomId": "OT-1401",
        "roomNo": "1401",
        "roomTypeId": "PRM",
        "date": "2026-06-09",
        "status": "in-house",
        "available": false,
        "rate": {
          "amount": 100,
          "currency": "USD"
        }
      },
      {
        "roomId": "OT-1402",
        "roomNo": "1402",
        "roomTypeId": "PRM",
        "date": "2026-06-09",
        "status": "in-house",
        "available": false,
        "rate": {
          "amount": 100,
          "currency": "USD"
        }
      },
      {
        "roomId": "OT-1403",
        "roomNo": "1403",
        "roomTypeId": "PRM",
        "date": "2026-06-09",
        "status": "in-house",
        "available": false,
        "rate": {
          "amount": 100,
          "currency": "USD"
        }
      },
      {
        "roomId": "OT-1405",
        "roomNo": "1405",
        "roomTypeId": "PRM",
        "date": "2026-06-09",
        "status": "out-of-service",
        "available": false,
        "rate": {
          "amount": 100,
          "currency": "USD"
        }
      },
      {
        "roomId": "FT-1201",
        "roomNo": "1201",
        "roomTypeId": "DLX",
        "date": "2026-06-09",
        "status": "in-house",
        "available": false,
        "rate": {
          "amount": 140,
          "currency": "USD"
        }
      },
      {
        "roomId": "FT-1202",
        "roomNo": "1202",
        "roomTypeId": "DLX",
        "date": "2026-06-09",
        "status": "in-house",
        "available": false,
        "rate": {
          "amount": 140,
          "currency": "USD"
        }
      },
      {
        "roomId": "FT-1203",
        "roomNo": "1203",
        "roomTypeId": "DLX",
        "date": "2026-06-09",
        "status": "in-house",
        "available": false,
        "rate": {
          "amount": 140,
          "currency": "USD"
        }
      },
      {
        "roomId": "FT-1205",
        "roomNo": "1205",
        "roomTypeId": "DLX",
        "date": "2026-06-09",
        "status": "vacant-clean",
        "available": true,
        "rate": {
          "amount": 140,
          "currency": "USD"
        }
      },
      {
        "roomId": "FT-1206",
        "roomNo": "1206",
        "roomTypeId": "DLX",
        "date": "2026-06-09",
        "status": "vacant-dirty",
        "available": true,
        "rate": {
          "amount": 140,
          "currency": "USD"
        }
      },
      {
        "roomId": "FT-0801",
        "roomNo": "0801",
        "roomTypeId": "STD",
        "date": "2026-06-09",
        "status": "in-house",
        "available": false,
        "rate": {
          "amount": 100,
          "currency": "USD"
        }
      },
      {
        "roomId": "FT-0802",
        "roomNo": "0802",
        "roomTypeId": "STD",
        "date": "2026-06-09",
        "status": "vacant-clean",
        "available": true,
        "rate": {
          "amount": 100,
          "currency": "USD"
        }
      },
      {
        "roomId": "FT-0803",
        "roomNo": "0803",
        "roomTypeId": "STD",
        "date": "2026-06-09",
        "status": "vacant-clean",
        "available": true,
        "rate": {
          "amount": 100,
          "currency": "USD"
        }
      },
      {
        "roomId": "LV-V01",
        "roomNo": "V-01",
        "roomTypeId": "VIL",
        "date": "2026-06-09",
        "status": "in-house",
        "available": false,
        "rate": {
          "amount": 380,
          "currency": "USD"
        }
      },
      {
        "roomId": "LV-V02",
        "roomNo": "V-02",
        "roomTypeId": "VIL",
        "date": "2026-06-09",
        "status": "vacant-clean",
        "available": true,
        "rate": {
          "amount": 380,
          "currency": "USD"
        }
      }
    ],
    "page": {
      "page": 1,
      "pageSize": 50,
      "total": 16,
      "totalPages": 1
    }
  },
  "meta": {
    "requestId": "REQ-ROOMS-AVAILABILITY",
    "tenantId": "TENANT-GRAND-SAIGON",
    "apiVersion": "v8",
    "generatedAt": "2026-06-09T09:00:00+09:00",
    "timezone": "Asia/Seoul",
    "currency": "USD"
  }
}
