{
  "success": true,
  "data": {
    "items": [
      {
        "id": "s1",
        "name": "Nguyen Kim",
        "init": "NK",
        "email": "kim@hotel.example",
        "roleId": "sys_admin",
        "status": "online",
        "last": "방금 전",
        "color": "#6D28D9",
        "tenantId": "TENANT-GRAND-SAIGON"
      },
      {
        "id": "s2",
        "name": "Robert Ford",
        "init": "RF",
        "email": "gm@hotel.example",
        "roleId": "sys_gm",
        "status": "online",
        "last": "10분 전",
        "color": "#111827",
        "tenantId": "TENANT-GRAND-SAIGON"
      },
      {
        "id": "s3",
        "name": "김지연",
        "init": "JK",
        "email": "sales@hotel.example",
        "roleId": "sys_desk",
        "status": "online",
        "last": "방금 전",
        "color": "#2563EB",
        "tenantId": "TENANT-GRAND-SAIGON"
      },
      {
        "id": "s4",
        "name": "Sarah Connor",
        "init": "SC",
        "email": "desk@hotel.example",
        "roleId": "sys_desk",
        "status": "offline",
        "last": "2시간 전",
        "color": "#2563EB",
        "tenantId": "TENANT-GRAND-SAIGON"
      },
      {
        "id": "s5",
        "name": "Maria Garcia",
        "init": "MG",
        "email": "housekeeping@hotel.example",
        "roleId": "sys_housekeeping",
        "status": "online",
        "last": "30분 전",
        "color": "#059669",
        "tenantId": "TENANT-GRAND-SAIGON"
      },
      {
        "id": "s7",
        "name": "김철수",
        "init": "CS",
        "email": "maintenance@hotel.example",
        "roleId": "sys_maintenance",
        "status": "online",
        "last": "방금 전",
        "color": "#D97706",
        "tenantId": "TENANT-GRAND-SAIGON"
      }
    ],
    "page": {
      "page": 1,
      "pageSize": 50,
      "total": 6,
      "totalPages": 1
    }
  },
  "meta": {
    "requestId": "REQ-ADMIN-TENANT-USERS",
    "tenantId": "TENANT-GRAND-SAIGON",
    "apiVersion": "v8",
    "generatedAt": "2026-05-28T09:00:00+09:00",
    "timezone": "Asia/Seoul",
    "currency": "KRW"
  }
}
