{
  "success": true,
  "data": {
    "items": [
      {
        "id": "MT-1001",
        "roomId": "OT-1405",
        "roomNo": "1405",
        "type": "aircon",
        "status": "in-progress",
        "priority": "high",
        "desc": "VIP 도착 전 냉방 성능 점검 및 필터 교체 필요",
        "assignee": "최동훈",
        "createdAt": "2026-06-07T09:00:00+09:00"
      },
      {
        "id": "MT-1002",
        "roomId": "FT-1206",
        "roomNo": "1206",
        "type": "plumbing",
        "status": "open",
        "priority": "normal",
        "desc": "욕실 배수 속도 저하, 샤워 후 바닥 물고임 발생",
        "assignee": "박미래",
        "createdAt": "2026-06-07T10:30:00+09:00"
      },
      {
        "id": "MT-1003",
        "roomId": "OT-PH01",
        "roomNo": "PH01",
        "type": "electrical",
        "status": "open",
        "priority": "urgent",
        "desc": "거실 메인 조명 스위치 반응 없음, 투숙객 재실 중 긴급 점검 요청",
        "assignee": "이영호",
        "createdAt": "2026-06-07T11:10:00+09:00"
      },
      {
        "id": "MT-1004",
        "roomId": "FT-1203",
        "roomNo": "1203",
        "type": "door",
        "status": "in-progress",
        "priority": "high",
        "desc": "객실 카드키 인식 지연, 3회 이상 태그해야 문 열림",
        "assignee": "김철수",
        "createdAt": "2026-06-07T08:40:00+09:00"
      },
      {
        "id": "MT-1005",
        "roomId": "OT-1401",
        "roomNo": "1401",
        "type": "furniture",
        "status": "done",
        "priority": "normal",
        "desc": "책상 의자 흔들림 보수 및 볼트 조임 완료",
        "assignee": "김철수",
        "createdAt": "2026-06-06T15:20:00+09:00"
      },
      {
        "id": "MT-1006",
        "roomId": "FT-0803",
        "roomNo": "0803",
        "type": "plumbing",
        "status": "done",
        "priority": "high",
        "desc": "세면대 수전 누수 패킹 교체 완료",
        "assignee": "박미래",
        "createdAt": "2026-06-06T13:15:00+09:00"
      },
      {
        "id": "MT-1007",
        "roomId": "LV-V-01",
        "roomNo": "V-01",
        "type": "aircon",
        "status": "open",
        "priority": "urgent",
        "desc": "풀빌라 실외기 이상 소음, 인접 객실 민원 접수",
        "assignee": "최동훈",
        "createdAt": "2026-06-07T12:05:00+09:00"
      },
      {
        "id": "MT-1008",
        "roomId": "OT-1403",
        "roomNo": "1403",
        "type": "elevator",
        "status": "open",
        "priority": "high",
        "desc": "오션타워 14층 엘리베이터 호출 버튼 점등 불량",
        "assignee": "미배정",
        "createdAt": "2026-06-07T13:25:00+09:00"
      },
      {
        "id": "MT-1009",
        "roomId": "FT-0801",
        "roomNo": "0801",
        "type": "electrical",
        "status": "done",
        "priority": "low",
        "desc": "침대 좌측 콘센트 커버 교체 완료",
        "assignee": "이영호",
        "createdAt": "2026-06-05T17:50:00+09:00"
      },
      {
        "id": "MT-1010",
        "roomId": "OT-PH02",
        "roomNo": "PH02",
        "type": "furniture",
        "status": "in-progress",
        "priority": "normal",
        "desc": "옷장 슬라이딩 도어 레일 이탈, 부품 확인 중",
        "assignee": "김철수",
        "createdAt": "2026-06-07T14:00:00+09:00"
      },
      {
        "id": "MT-1011",
        "roomId": "FT-1205",
        "roomNo": "1205",
        "type": "other",
        "status": "open",
        "priority": "normal",
        "desc": "발코니 방충망 찢어짐, 체크아웃 후 교체 필요",
        "assignee": "미배정",
        "createdAt": "2026-06-07T14:25:00+09:00"
      },
      {
        "id": "MT-1012",
        "roomId": "FT-0802",
        "roomNo": "0802",
        "type": "door",
        "status": "done",
        "priority": "normal",
        "desc": "욕실 도어 손잡이 헐거움 보수 완료",
        "assignee": "김철수",
        "createdAt": "2026-06-05T11:35:00+09:00"
      }
    ],
    "page": {
      "page": 1,
      "pageSize": 50,
      "total": 12,
      "totalPages": 1
    }
  },
  "meta": {
    "requestId": "REQ-MAINTENANCE-REQUESTS",
    "tenantId": "TENANT-GRAND-SAIGON",
    "apiVersion": "v8",
    "generatedAt": "2026-06-07T15:00:00+09:00",
    "timezone": "Asia/Seoul",
    "currency": "USD"
  }
}
