{
  "success": true,
  "data": {
    "items": [
      {
        "id": "ORD-5001",
        "roomId": "OT-1401",
        "roomNo": "1401",
        "items": [
          "클럽 샌드위치",
          "아메리카노 2"
        ],
        "total": {
          "amount": 45,
          "currency": "USD"
        },
        "status": "preparing",
        "time": "11:05"
      },
      {
        "id": "ORD-5002",
        "roomId": "OT-PH01",
        "roomNo": "PH01",
        "items": [
          "조식 세트 A"
        ],
        "total": {
          "amount": 85,
          "currency": "USD"
        },
        "status": "done",
        "time": "07:30"
      }
    ],
    "page": {
      "page": 1,
      "pageSize": 50,
      "total": 2,
      "totalPages": 1
    }
  },
  "meta": {
    "requestId": "REQ-POS-ORDERS",
    "tenantId": "TENANT-GRAND-SAIGON",
    "apiVersion": "v8",
    "generatedAt": "2026-06-09T09:00:00+09:00",
    "timezone": "Asia/Seoul",
    "currency": "USD"
  }
}
