{
  "success": true,
  "data": {
    "items": [
      {
        "id": "EVT-001",
        "type": "frontdesk.room-change",
        "category": "frontdesk",
        "severity": "info",
        "icon": "fa-right-left",
        "title": {
          "ko": "객실 변경 공유",
          "en": "Room change shared"
        },
        "label": {
          "ko": "Nguyen Thi Lan 예약이 1201호에서 1203호로 변경되었습니다.",
          "en": "Nguyen Thi Lan was moved from room 1201 to 1203."
        },
        "desc": {
          "ko": "프런트에서 객실 이동을 처리했습니다. 정산과 청소 확인 시 변경된 호실 기준으로 확인하세요.",
          "en": "Front desk processed the room move. Review settlement and cleaning by the new room."
        },
        "time": "08:25",
        "eventDate": "2026-06-10",
        "actor": "Front Desk Kim",
        "roomNo": "1203",
        "reservationId": "RSV-0003",
        "target": "frontdesk/reservation-board.html?query=1203"
      },
      {
        "id": "EVT-002",
        "type": "ancillary.pos-order",
        "category": "ancillary",
        "severity": "info",
        "icon": "fa-cash-register",
        "title": {
          "ko": "POS 주문 등록",
          "en": "POS order added"
        },
        "label": {
          "ko": "1206호 객실에 룸서비스 POS 주문이 등록되었습니다.",
          "en": "A room-service POS order was added to room 1206."
        },
        "desc": {
          "ko": "객실 정산에 합산될 주문입니다. 체크아웃 전 Folio 반영 여부를 확인하세요.",
          "en": "This order should flow into the room folio before checkout."
        },
        "time": "09:05",
        "eventDate": "2026-06-10",
        "actor": "POS Lee",
        "roomNo": "1206",
        "target": "operations/ancillary.html?query=1206"
      },
      {
        "id": "EVT-003",
        "type": "ancillary.rentacar",
        "category": "ancillary",
        "severity": "info",
        "icon": "fa-car",
        "title": {
          "ko": "렌터카 예약 등록",
          "en": "Rent-a-car booking added"
        },
        "label": {
          "ko": "V-01 단체 객실에 공항 샌딩 렌터카 예약이 등록되었습니다.",
          "en": "Airport drop-off rent-a-car was added for group room V-01."
        },
        "desc": {
          "ko": "이용일이 오늘이 아닐 수 있으므로 부가서비스 일정과 단체 정산 연결을 함께 확인합니다.",
          "en": "Check service date and group settlement linkage because usage may be on a later date."
        },
        "time": "09:40",
        "eventDate": "2026-06-10",
        "serviceDate": "2026-06-13",
        "actor": "Concierge Ana",
        "roomNo": "V-01",
        "target": "operations/ancillary.html?query=V-01"
      },
      {
        "id": "EVT-004",
        "type": "ancillary.golf",
        "category": "ancillary",
        "severity": "info",
        "icon": "fa-golf-ball-tee",
        "title": {
          "ko": "골프 티타임 변경",
          "en": "Golf tee time changed"
        },
        "label": {
          "ko": "PH01 고객의 골프 티타임이 07:30에서 08:10으로 변경되었습니다.",
          "en": "Room PH01 golf tee time changed from 07:30 to 08:10."
        },
        "desc": {
          "ko": "프런트와 컨시어지가 같은 변경 정보를 확인해야 하는 공유 이벤트입니다.",
          "en": "Front desk and concierge should share the same changed schedule."
        },
        "time": "10:10",
        "eventDate": "2026-06-10",
        "serviceDate": "2026-06-11",
        "actor": "Concierge Park",
        "roomNo": "PH01",
        "target": "operations/ancillary.html?query=PH01"
      },
      {
        "id": "EVT-005",
        "type": "billing.payment",
        "category": "billing",
        "severity": "info",
        "icon": "fa-credit-card",
        "title": {
          "ko": "예치금 수납",
          "en": "Deposit payment received"
        },
        "label": {
          "ko": "1209호 예약에 예치금 ₱10,000이 수납되었습니다.",
          "en": "A ₱10,000 deposit was received for room 1209."
        },
        "desc": {
          "ko": "체크아웃 정산 시 예치금 차감 여부를 정산현황에서 확인하세요.",
          "en": "Confirm deposit deduction in settlement status at checkout."
        },
        "time": "10:55",
        "eventDate": "2026-06-10",
        "actor": "Cashier Mina",
        "roomNo": "1209",
        "folioId": "FOL-260002",
        "target": "operations/settlement-status.html?query=1209"
      },
      {
        "id": "EVT-006",
        "type": "group.rooming-list",
        "category": "group",
        "severity": "info",
        "icon": "fa-users-line",
        "title": {
          "ko": "단체 투숙객 명단 변경",
          "en": "Group rooming list changed"
        },
        "label": {
          "ko": "Samsung Tech Conference 2026 객실 명단 2건이 변경되었습니다.",
          "en": "Two rooming-list entries changed for Samsung Tech Conference 2026."
        },
        "desc": {
          "ko": "대표자, 객실 배정, 정산 기준이 같이 바뀔 수 있어 단체 상세에서 확인합니다.",
          "en": "Representative, room assignment, and settlement basis may be affected."
        },
        "time": "11:20",
        "eventDate": "2026-06-10",
        "actor": "Sales Nguyen",
        "groupId": "GRP-260527-01",
        "target": "frontdesk/groups_block_detail.html?id=GRP-260527-01"
      },
      {
        "id": "EVT-007",
        "type": "approval.refund",
        "category": "approval",
        "severity": "urgent",
        "icon": "fa-circle-exclamation",
        "title": {
          "ko": "환불 승인 필요",
          "en": "Refund approval required"
        },
        "label": {
          "ko": "체크아웃 완료 Folio에 과수납 환불 확인이 필요합니다.",
          "en": "An overpayment refund needs approval on a checked-out folio."
        },
        "desc": {
          "ko": "승인이 필요한 정산 이벤트입니다. 정산현황에서 Folio를 확인하세요.",
          "en": "This settlement event requires approval. Review the folio in settlement status."
        },
        "time": "12:05",
        "eventDate": "2026-06-10",
        "actor": "Cashier Mina",
        "folioId": "FOL-260003",
        "urgent": true,
        "target": "operations/settlement-status.html?filter=all&query=FOL-260003"
      },
      {
        "id": "EVT-008",
        "type": "frontdesk.cleaning-state",
        "category": "frontdesk",
        "severity": "info",
        "icon": "fa-broom",
        "title": {
          "ko": "청소 상태 변경",
          "en": "Cleaning state changed"
        },
        "label": {
          "ko": "1205호가 청소 완료로 변경되어 체크인 가능 상태가 되었습니다.",
          "en": "Room 1205 changed to clean and is now ready for check-in."
        },
        "desc": {
          "ko": "하우스키핑 앱을 쓰지 않는 동안 프런트가 객실 상태 변경을 공유하는 이벤트입니다.",
          "en": "Front desk shares this room-state event while the housekeeping app is not used."
        },
        "time": "13:30",
        "eventDate": "2026-06-10",
        "actor": "Front Desk Kim",
        "roomNo": "1205",
        "target": "frontdesk/reservation-board.html?query=1205"
      },
      {
        "id": "EVT-009",
        "type": "frontdesk.maintenance-state",
        "category": "frontdesk",
        "severity": "urgent",
        "icon": "fa-screwdriver-wrench",
        "title": {
          "ko": "점검 중 전환",
          "en": "Room set to maintenance"
        },
        "label": {
          "ko": "1405호가 점검 중으로 변경되어 판매/체크인 제한이 필요합니다.",
          "en": "Room 1405 was set to maintenance and should be blocked from sale/check-in."
        },
        "desc": {
          "ko": "시설보수 메뉴를 쓰지 않아도 프런트 예약현황에서 점검 상태를 공유합니다.",
          "en": "Maintenance state is shared on the reservation board even without the maintenance module."
        },
        "time": "14:15",
        "eventDate": "2026-06-10",
        "actor": "Front Desk Lee",
        "roomNo": "1405",
        "urgent": true,
        "target": "frontdesk/reservation-board.html?query=1405"
      },
      {
        "id": "EVT-010",
        "type": "system.audit-log",
        "category": "system",
        "severity": "info",
        "icon": "fa-shield-halved",
        "title": {
          "ko": "감사 로그 기록",
          "en": "Audit log recorded"
        },
        "label": {
          "ko": "정산 수납 취소 시도와 고객 연락처 열람이 감사 로그에 기록되었습니다.",
          "en": "A payment-cancel attempt and guest-contact access were recorded in audit logs."
        },
        "desc": {
          "ko": "공유 알림으로 보이지만 원천은 운영/감사 로그에 남아야 하는 이벤트입니다.",
          "en": "This alert is shared, but its source should remain in operation/audit logs."
        },
        "time": "15:00",
        "eventDate": "2026-06-10",
        "actor": "System",
        "target": "settings/audit-logs.html"
      },
      {
        "id": "EVT-DEMO-0708-001",
        "type": "frontdesk.arrival-delay",
        "category": "frontdesk",
        "severity": "warning",
        "icon": "fa-user-clock",
        "title": {
          "ko": "미도착 예약 확인",
          "en": "Not-arrived booking review"
        },
        "label": {
          "ko": "1222호 예약이 입실 예정일을 지났지만 아직 도착하지 않았습니다.",
          "en": "Room 1222 booking has not arrived after its check-in date."
        },
        "desc": {
          "ko": "예약현황에서 미도착 배지와 체크인 가능 여부를 확인합니다.",
          "en": "Review the Not Arrived badge and check-in availability on the room board."
        },
        "time": "09:10",
        "eventDate": "2026-06-10",
        "actor": "Front Desk Kim",
        "roomNo": "1222",
        "target": "frontdesk/reservation-board.html?query=1222"
      },
      {
        "id": "EVT-DEMO-0708-002",
        "type": "billing.settlement-needed",
        "category": "billing",
        "severity": "urgent",
        "icon": "fa-file-invoice-dollar",
        "title": {
          "ko": "체크아웃 정산 필요",
          "en": "Checkout settlement needed"
        },
        "label": {
          "ko": "1205호 Maria Santos 체크아웃 정산에 미수금이 남아 있습니다.",
          "en": "Room 1205 Maria Santos has an outstanding checkout balance."
        },
        "desc": {
          "ko": "정산현황에서 수납 후 정산 완료 처리해야 합니다.",
          "en": "Collect payment and complete settlement in Settlement Status."
        },
        "time": "10:20",
        "eventDate": "2026-06-10",
        "actor": "Cashier Mina",
        "roomNo": "1205",
        "folioId": "FOL-DEMO-0708-1205-UNPAID",
        "target": "operations/settlement-status.html?query=1205"
      },
      {
        "id": "EVT-DEMO-0708-003",
        "type": "ancillary.golf",
        "category": "ancillary",
        "severity": "info",
        "icon": "fa-golf-ball-tee",
        "title": {
          "ko": "골프 바우처 출력 대기",
          "en": "Golf voucher pending"
        },
        "label": {
          "ko": "1218호 고객의 18홀 그린피 바우처 출력이 필요합니다.",
          "en": "Room 1218 guest needs an 18-hole golf voucher."
        },
        "desc": {
          "ko": "부가서비스 상세에서 골프장 바우처를 확인하고 출력합니다.",
          "en": "Open ancillary detail to review and print the golf voucher."
        },
        "time": "11:45",
        "eventDate": "2026-06-10",
        "serviceDate": "2026-06-10",
        "actor": "Concierge Park",
        "roomNo": "1218",
        "target": "operations/ancillary.html?service=golf&query=1218"
      },
      {
        "id": "EVT-DEMO-0708-004",
        "type": "group.arrival",
        "category": "group",
        "severity": "info",
        "icon": "fa-users-line",
        "title": {
          "ko": "단체 도착 준비",
          "en": "Group arrival preparation"
        },
        "label": {
          "ko": "Nguyen 가족 모임 2실이 금일 도착 예정입니다.",
          "en": "Nguyen family group has two rooms arriving today."
        },
        "desc": {
          "ko": "일반인 대표 단체 케이스로 객실 배정과 투숙객 명단을 확인합니다.",
          "en": "Review room allocation and rooming list for the private group leader case."
        },
        "time": "12:30",
        "eventDate": "2026-06-10",
        "actor": "Sales Nguyen",
        "groupId": "GRP-DEMO-THU-PRIVATE",
        "target": "frontdesk/groups_block_detail.html?id=GRP-DEMO-THU-PRIVATE"
      },
      {
        "id": "EVT-DEMO-0708-005",
        "type": "housekeeping.cleaning",
        "category": "housekeeping",
        "severity": "info",
        "icon": "fa-broom",
        "title": {
          "ko": "체크인 전 청소 확인",
          "en": "Pre-check-in cleaning check"
        },
        "label": {
          "ko": "1213호 VIP 체크인 전 청소 필요 상태입니다.",
          "en": "Room 1213 needs cleaning before VIP check-in."
        },
        "desc": {
          "ko": "예약현황에서 청소 상태를 확인 후 체크인 가능 여부를 판단합니다.",
          "en": "Check cleaning status on the room board before check-in."
        },
        "time": "13:05",
        "eventDate": "2026-06-10",
        "actor": "HK Tran",
        "roomNo": "1213",
        "target": "frontdesk/reservation-board.html?query=1213"
      }
    ],
    "page": {
      "page": 1,
      "pageSize": 50,
      "total": 15,
      "totalPages": 1
    }
  },
  "meta": {
    "requestId": "REQ-DASHBOARD-EVENT-NOTIFICATIONS",
    "tenantId": "TENANT-GRAND-SAIGON",
    "apiVersion": "v10",
    "generatedAt": "2026-06-10T09:00:00+09:00",
    "timezone": "Asia/Seoul",
    "currency": "PHP"
  }
}
